linkit/__init__.py
linkit/__version__.py
linkit/apps.py
linkit/form_fields.py
linkit/link.py
linkit/model_fields.py
linkit/models.py
linkit/types.py
linkit/widgets.py
linkit/migrations/0001_initial.py
linkit/migrations/__init__.py
linkit/templates/django/forms/widgets/link.html
linkit/types/__init__.py
linkit/types/contracts.py
linkit/types/file.py
linkit/types/input.py
linkit/types/manager.py
linkit/types/model.py
linkit/types/page.py
linkit-0.1.6.dist-info/LICENSE
linkit-0.1.6.dist-info/METADATA
linkit-0.1.6.dist-info/WHEEL
linkit-0.1.6.dist-info/top_level.txt
linkit-0.1.6.dist-info/RECORD
