Metadata-Version: 2.1
Name: linkit
Version: 0.1.6
Summary: Painless link handling - be it a custom model, file or cms page
Home-page: https://github.com/dreipol/linkit
Author: dreipol
Author-email: dev@dreipol.ch
License: MIT
Platform: UNKNOWN
Classifier: License :: OSI Approved :: MIT License
Classifier: Programming Language :: Python
Classifier: Programming Language :: Python :: 3
Classifier: Programming Language :: Python :: 3.6
Classifier: Programming Language :: Python :: Implementation :: CPython
Classifier: Programming Language :: Python :: Implementation :: PyPy
Requires-Python: >=3.6.0
